adder.t.v
// Adder testbench
`timescale 1 ns / 1 ps
`include "adder.v"

module testFullAdder();
    reg a, b, carryin;
    wire sum, carryout;
    wire xor1, and1, and2, or1;

    //behavioralFullAdder adder (sum, carryout, a, b, carryin);
    structuralFullAdder adder (sum, carryout, a, b, carryin, xor1, and1, and2, or1);

initial begin
    $dumpfile("adder.vcd");
    $dumpvars();
    $display("Carryin A B| Carryout sum | Expected C Expected S");
    a=0;b=0;carryin=0; #1000 
    $display("   %b  %b  %b |        %b   %b | Expected 0 Expected 0", carryin, a, b, carryout, sum);
    a=0;b=0;carryin=1; #1000 
    $display("   %b  %b  %b |        %b   %b | Expected 0 Expected 1", carryin, a, b, carryout, sum);
    a=0;b=1;carryin=0; #1000 
    $display("   %b  %b  %b |        %b   %b | Expected 0 Expected 1", carryin, a, b, carryout, sum);
    a=0;b=1;carryin=1; #1000 
    $display("   %b  %b  %b |        %b   %b | Expected 1 Expected 0", carryin, a, b, carryout, sum);
    a=1;b=0;carryin=0; #1000 
    $display("   %b  %b  %b |        %b   %b | Expected 0 Expected 1", carryin, a, b, carryout, sum);
    a=1;b=0;carryin=1; #1000 
    $display("   %b  %b  %b |        %b   %b | Expected 1 Expected 0", carryin, a, b, carryout, sum);
    a=1;b=1;carryin=0; #1000 
    $display("   %b  %b  %b |        %b   %b | Expected 1 Expected 0", carryin, a, b, carryout, sum);
    a=1;b=1;carryin=1; #1000 
    $display("   %b  %b  %b |        %b   %b | Expected 1 Expected 1", carryin, a, b, carryout, sum);
    $finish();
    end

endmodule

adder.v
// Adder circuit
// define gates with delays
`define AND and #50
`define OR or #50
`define NOT not #50
`define XOR xor #50

module behavioralFullAdder
(
    output sum, 
    output carryout,
    input a, 
    input b, 
    input carryin
);
    // Uses concatenation operator and built-in '+'
    assign {carryout, sum}=a+b+carryin;
endmodule

module structuralFullAdder
(
    output sum, 
    output carryout,
    input a, 
    input b, 
    input carryin,
    output xor1, and1, and2, or1
);
    // Your adder code here
    xor xorgate1(xor1, a, b);
    xor xorgate2(sum, xor1, carryin);
    and andgate1(and1, carryin, xor1);
    and andgate2(and2, a, b);
    or orgate(carryout, and1, and2);



endmodule

adder.vcd
$date
	Fri Sep 21 10:13:47 2018
$end
$version
	Icarus Verilog
$end
$timescale
	1ps
$end
$scope module behavioralFullAdder $end
$var wire 1 ! a $end
$var wire 1 " b $end
$var wire 1 # carryin $end
$var wire 1 $ sum $end
$var wire 1 % carryout $end
$upscope $end
$scope module testFullAdder $end
$var wire 1 & or1 $end
$var wire 1 ' xor1 $end
$var wire 1 ( sum $end
$var wire 1 ) carryout $end
$var wire 1 * and2 $end
$var wire 1 + and1 $end
$var reg 1 , a $end
$var reg 1 - b $end
$var reg 1 . carryin $end
$scope module adder $end
$var wire 1 , a $end
$var wire 1 + and1 $end
$var wire 1 * and2 $end
$var wire 1 - b $end
$var wire 1 . carryin $end
$var wire 1 ) carryout $end
$var wire 1 & or1 $end
$var wire 1 ( sum $end
$var wire 1 ' xor1 $end
$upscope $end
$upscope $end
$enddefinitions $end
#0
$dumpvars
0.
0-
0,
0+
0*
0)
0(
0'
z&
x%
x$
z#
z"
z!
$end
#1000000
1(
1.
#2000000
1'
0.
1-
#3000000
1)
0(
1+
1.
#4000000
0)
1(
0+
0.
0-
1,
#5000000
1)
0(
1+
1.
#6000000
0+
0'
1*
0.
1-
#7000000
1(
1.
