decoder.t.v
// Decoder testbench
`timescale 1 ns / 1 ps
`include "decoder.v"

module testDecoder (); 
    reg addr0, addr1;
    reg enable;
    wire out0,out1,out2,out3;
    wire naddress0,naddress1;
   

    //behavioralDecoder decoder (out0,out1,out2,out3,addr0,addr1,enable);
    structuralDecoder decoder (out0,out1,out2,out3,addr0,addr1,enable,naddress0,naddress1); // Swap after testing
 
    initial begin
    $dumpfile("decoder.vcd");
    $dumpvars();
    $display("En A0 A1| O0 O1 O2 O3 | Expected Output");
    enable=0;addr0=0;addr1=0; #1000 
    $display("%b  %b  %b |  %b  %b  %b  %b | All false", enable, addr0, addr1, out0, out1, out2, out3);
    enable=0;addr0=1;addr1=0; #1000
    $display("%b  %b  %b |  %b  %b  %b  %b | All false", enable, addr0, addr1, out0, out1, out2, out3);
    enable=0;addr0=0;addr1=1; #1000 
    $display("%b  %b  %b |  %b  %b  %b  %b | All false", enable, addr0, addr1, out0, out1, out2, out3);
    enable=0;addr0=1;addr1=1; #1000 
    $display("%b  %b  %b |  %b  %b  %b  %b | All false", enable, addr0, addr1, out0, out1, out2, out3);
    enable=1;addr0=0;addr1=0; #1000 
    $display("%b  %b  %b |  %b  %b  %b  %b | O0 Only", enable, addr0, addr1, out0, out1, out2, out3);
    enable=1;addr0=1;addr1=0; #1000 
    $display("%b  %b  %b |  %b  %b  %b  %b | O1 Only", enable, addr0, addr1, out0, out1, out2, out3);
    enable=1;addr0=0;addr1=1; #1000 
    $display("%b  %b  %b |  %b  %b  %b  %b | O2 Only", enable, addr0, addr1, out0, out1, out2, out3);
    enable=1;addr0=1;addr1=1; #1000 
    $display("%b  %b  %b |  %b  %b  %b  %b | O3 Only", enable, addr0, addr1, out0, out1, out2, out3);
    $finish();
    end

endmodule

decoder.v
// Decoder circuit
`define AND and #50
`define OR or #50
`define NOT not #50
`define XOR xor #50

module behavioralDecoder
(
    output out0, out1, out2, out3,
    input address0, address1,
    input enable
);
    // Uses concatenation and shift operators
    assign {out3,out2,out1,out0}=enable<<{address1,address0};
endmodule


module structuralDecoder
(
    output out0, out1, out2, out3,
    input addr0, addr1,
    input enable,
    output naddress0, naddress1
);
    wire naddress0; 
    wire naddress1;
    not Ad0inv(naddress0, addr0); //inverted named Ad0inv, takes address00 and produces signal naddress0
    not Ad1inv(naddress1, addr1); //inverted named Ad0inv, takes address00 and produces signal naddress0
    and andgate0(out0, naddress0, naddress1, enable); 	// AND gate produces out0 from naddress0 and naddress1
    and andgate1(out1, addr0, naddress1, enable); 	// AND gate produces out1 from address0 and naddress1
    and andgate2(out2, naddress0, addr1, enable); 	// AND gate produces out2 from naddress0 and address1
    and andgate3(out3, addr0, addr1, enable); 	        // AND gate produces out3 from address0 and address1



// Your decoder code here
endmodule

decoder.vcd
$date
	Fri Sep 21 10:08:51 2018
$end
$version
	Icarus Verilog
$end
$timescale
	1ps
$end
$scope module behavioralDecoder $end
$var wire 1 ! address0 $end
$var wire 1 " address1 $end
$var wire 1 # enable $end
$var wire 1 $ out3 $end
$var wire 1 % out2 $end
$var wire 1 & out1 $end
$var wire 1 ' out0 $end
$upscope $end
$scope module testDecoder $end
$var wire 1 ( out3 $end
$var wire 1 ) out2 $end
$var wire 1 * out1 $end
$var wire 1 + out0 $end
$var wire 1 , naddress1 $end
$var wire 1 - naddress0 $end
$var reg 1 . addr0 $end
$var reg 1 / addr1 $end
$var reg 1 0 enable $end
$scope module decoder $end
$var wire 1 . addr0 $end
$var wire 1 / addr1 $end
$var wire 1 0 enable $end
$var wire 1 - naddress0 $end
$var wire 1 , naddress1 $end
$var wire 1 + out0 $end
$var wire 1 * out1 $end
$var wire 1 ) out2 $end
$var wire 1 ( out3 $end
$upscope $end
$upscope $end
$enddefinitions $end
#0
$dumpvars
00
0/
0.
1-
1,
0+
0*
0)
0(
x'
x&
x%
x$
z#
z"
z!
$end
#1000000
0-
1.
#2000000
0,
1-
1/
0.
#3000000
0-
1.
#4000000
1+
1,
1-
0/
0.
10
#5000000
0+
0-
1*
1.
#6000000
0,
1)
1-
0*
1/
0.
#7000000
0)
0-
1(
1.
